<?xml version="1.0" encoding="UTF-8"?>
<con:soapui-project id="d33d39b0-b432-4bf8-8bae-02f4d9c29f39" activeEnvironment="Default" name="OAuthServer" soapui-version="5.2.1" abortOnError="false" runType="SEQUENTIAL" xmlns:con="http://eviware.com/soapui/config"><con:settings/><con:interface xsi:type="con:RestService" id="b6cc130d-fc1c-4659-8d62-e9c8cded77cf" wadlVersion="http://wadl.dev.java.net/2009/02" name="http://localhost:8050" type="rest" xmlns:xsi="http://www.w3.org/2001/XMLSchema-instance"><con:settings/><con:definitionCache/><con:endpoints><con:endpoint>http://localhost:8050</con:endpoint></con:endpoints><con:resource name="properties" path="/oauth2/properties" id="8916bdad-ac20-458d-b867-3751e8dc2953"><con:settings/><con:parameters/><con:method name="oauth-properties" id="e689e5cd-7481-4f6f-bbc6-0d86600f8aa6" method="GET"><con:settings/><con:parameters/><con:representation type="RESPONSE"><con:mediaType>application/json;charset=UTF-8</con:mediaType><con:status>200</con:status><con:params/></con:representation><con:request name="getAllProperties" id="d9953733-6cc3-4858-b09d-5db4e701149e" mediaType="application/json"><con:settings><con:setting id="com.eviware.soapui.impl.wsdl.WsdlRequest@request-headers">&lt;xml-fragment/></con:setting></con:settings><con:endpoint>http://localhost:8050</con:endpoint><con:request/><con:originalUri>http://localhost/oauth2/properties</con:originalUri><con:credentials><con:authType>No Authorization</con:authType></con:credentials><con:jmsConfig JMSDeliveryMode="PERSISTENT"/><con:jmsPropertyConfig/><con:parameters/></con:request></con:method></con:resource><con:resource name="token" path="/oauth2/token" id="2df39540-ba7e-4463-8e0f-43e347b6ff13"><con:settings/><con:parameters><con:parameter><con:name>grant_type</con:name><con:value/><con:style>QUERY</con:style><con:default/><con:description xsi:nil="true"/></con:parameter><con:parameter><con:name>refresh_token</con:name><con:value/><con:style>QUERY</con:style><con:default/><con:description xsi:nil="true"/></con:parameter></con:parameters><con:method name="refresh-token" id="d0d09b26-e7b4-4fe2-9fe1-5071902e3c00" method="POST"><con:settings/><con:parameters/><con:representation type="REQUEST"><con:mediaType>application/json</con:mediaType><con:params/></con:representation><con:representation type="RESPONSE"><con:mediaType>application/json;charset=UTF-8</con:mediaType><con:status>200</con:status><con:params/><con:element xmlns:tok="http://localhost/oauth2/token">tok:Response</con:element></con:representation><con:request name="refresh-token" id="3cde7b48-c72f-4023-8721-af2d89cdc539" mediaType="application/json" postQueryString="false"><con:settings><con:setting id="com.eviware.soapui.impl.wsdl.WsdlRequest@request-headers">&lt;xml-fragment/></con:setting></con:settings><con:endpoint>http://localhost:8050</con:endpoint><con:request/><con:originalUri>http://localhost/oauth2/token</con:originalUri><con:credentials><con:authType>No Authorization</con:authType></con:credentials><con:jmsConfig JMSDeliveryMode="PERSISTENT"/><con:jmsPropertyConfig/><con:parameters>
  <con:entry key="refresh_token" value="6850a7d81036975b6e823a92f4a1e4e7"/>
  <con:entry key="grant_type" value="REFRESH_TOKEN"/>
</con:parameters><con:parameterOrder><con:entry>grant_type</con:entry><con:entry>refresh_token</con:entry></con:parameterOrder></con:request></con:method></con:resource><con:resource name="validate" path="/oauth2/token/validate" id="b3f1c4e8-85b0-4bc3-acb4-c7ba03a30c9f"><con:settings/><con:parameters><con:parameter><con:name>access_token</con:name><con:value/><con:style>QUERY</con:style><con:default/><con:description xsi:nil="true"/></con:parameter></con:parameters><con:method name="validate" id="6c7007f3-ff5e-4fe4-bfe2-9873bc46e621" method="GET"><con:settings/><con:parameters/><con:representation type="RESPONSE"><con:mediaType>application/json;charset=UTF-8</con:mediaType><con:status>200</con:status><con:params/><con:element xmlns:val="http://localhost/oauth2/token/validate">val:Response</con:element></con:representation><con:request name="access-validate" id="e67e4163-dc08-4717-a5fa-1b6071ba7974" mediaType="application/json"><con:settings><con:setting id="com.eviware.soapui.impl.wsdl.WsdlRequest@request-headers">&lt;xml-fragment/></con:setting></con:settings><con:endpoint>http://localhost:8050</con:endpoint><con:request/><con:originalUri>http://localhost/oauth2/token/validate</con:originalUri><con:credentials><con:authType>No Authorization</con:authType></con:credentials><con:jmsConfig JMSDeliveryMode="PERSISTENT"/><con:jmsPropertyConfig/><con:parameters><entry key="access_token" value="223c8484b77fda5aeb2d2541e3c4da4a" xmlns="http://eviware.com/soapui/config"/></con:parameters><con:parameterOrder><con:entry>access_token</con:entry></con:parameterOrder></con:request></con:method></con:resource><con:resource name="token" path="/oauth2/token" id="5ce623b0-1cf7-4a87-83f7-3edbd5252d2e"><con:settings/><con:parameters><con:parameter><con:name>client_id</con:name><con:value/><con:style>QUERY</con:style><con:default/><con:description xsi:nil="true"/></con:parameter><con:parameter><con:name>client_secret</con:name><con:value/><con:style>QUERY</con:style><con:default/><con:description xsi:nil="true"/></con:parameter><con:parameter><con:name>username</con:name><con:value/><con:style>QUERY</con:style><con:default/><con:description xsi:nil="true"/></con:parameter><con:parameter><con:name>password</con:name><con:value/><con:style>QUERY</con:style><con:default/><con:description xsi:nil="true"/></con:parameter><con:parameter><con:name>grant_type</con:name><con:value/><con:style>QUERY</con:style><con:default/><con:description xsi:nil="true"/></con:parameter><con:parameter><con:name>redirect_uri</con:name><con:value/><con:style>QUERY</con:style><con:default/><con:description xsi:nil="true"/></con:parameter></con:parameters><con:method name="access-token" id="b41e2a72-d58b-46d0-be8a-1779fdae1288" method="POST"><con:settings/><con:parameters/><con:representation type="FAULT"><con:mediaType>text/html;charset=utf-8</con:mediaType><con:status>405</con:status><con:params/><con:element>html</con:element></con:representation><con:representation type="RESPONSE"><con:mediaType>application/json;charset=UTF-8</con:mediaType><con:status>200</con:status><con:params/><con:element xmlns:tok="http://localhost/oauth2/token">tok:Response</con:element></con:representation><con:representation type="REQUEST"><con:mediaType>application/x-www-form-urlencoded</con:mediaType><con:params/></con:representation><con:representation type="RESPONSE"><con:mediaType xsi:nil="true"/><con:status>0</con:status><con:params/><con:element>data</con:element></con:representation><con:representation type="FAULT"><con:mediaType>application/json;charset=UTF-8</con:mediaType><con:status>401</con:status><con:params/><con:element xmlns:tok="http://localhost/oauth2/token">tok:Fault</con:element></con:representation><con:request name="access-token" id="68415b84-7002-40fb-b4a0-455c192eaae7" mediaType="application/x-www-form-urlencoded" postQueryString="false"><con:settings><con:setting id="com.eviware.soapui.impl.wsdl.WsdlRequest@request-headers">&lt;xml-fragment/></con:setting></con:settings><con:endpoint>http://localhost:8050</con:endpoint><con:request/><con:originalUri>http://localhost/oauth2/token</con:originalUri><con:credentials><con:authType>No Authorization</con:authType></con:credentials><con:jmsConfig JMSDeliveryMode="PERSISTENT"/><con:jmsPropertyConfig/><con:parameters>
  <con:entry key="password" value="abhi1234"/>
  <con:entry key="grant_type" value="PASSWORD"/>
  <con:entry key="client_secret" value="1234567890"/>
  <con:entry key="redirect_uri" value="http://localhost:8050"/>
  <con:entry key="client_id" value="NGL_Web_1234"/>
  <con:entry key="username" value="abhi001"/>
</con:parameters><con:parameterOrder><con:entry>client_id</con:entry><con:entry>client_secret</con:entry><con:entry>username</con:entry><con:entry>password</con:entry><con:entry>grant_type</con:entry><con:entry>redirect_uri</con:entry></con:parameterOrder></con:request></con:method></con:resource></con:interface><con:properties/><con:wssContainer/><con:oAuth2ProfileContainer/><con:sensitiveInformation/></con:soapui-project>